<?xml version="1.0" encoding="utf-8"?>
<doctrine-mapping xmlns="http://doctrine-project.org/schemas/orm/doctrine-mapping" xmlns:xsi="http://www.w3.org/2001/XMLSchema-instance" xsi:schemaLocation="http://doctrine-project.org/schemas/orm/doctrine-mapping http://doctrine-project.org/schemas/orm/doctrine-mapping.xsd">
  <entity name="ContentArenaLayerBundle\Entity\FieldTermFrom" table="field_term_from">
    <indexes>
      <index name="data" columns="data"/>
    </indexes>
    <id name="pagesId" type="integer" column="pages_id">
      <generator strategy="IDENTITY"/>
    </id>
    <field name="data" type="datetime" column="data" nullable="false"/>
  </entity>
</doctrine-mapping>
